{"list":[{"date":"2017-10","arr":{"text":["123突击队","纪念一下第一次上警体课","警体课不就是用来装逼的吗","万圣节狂欢，你们有南瓜灯吗","万圣节狂欢，你们有糖果吗","万圣节狂欢，看到这些南瓜灯，你害怕吗"],"type":["image","image","image","image","image","image"],"month":10,"link":["2017-10-17_123突击队.jpg","2017-10-17_纪念一下第一次上警体课.jpg","2017-10-17_警体课不就是用来装逼的吗.jpg","2017-10-31_万圣节狂欢，你们有南瓜灯吗.jpg","2017-10-31_万圣节狂欢，你们有糖果吗.jpg","2017-10-31_万圣节狂欢，看到这些南瓜灯，你害怕吗.jpg"],"year":2017}},{"date":"2015-12","arr":{"text":["张昊的精彩瞬间"],"type":["image"],"month":12,"link":["2015-12-07_张昊的精彩瞬间.jpg"],"year":2015}},{"date":"2015-10","arr":{"text":["在文化广场进行拔河比赛，我们区队拿了第一。这天天气很好，后面一群其他专业的学生在训练","大一的小五"],"type":["image","image"],"month":10,"link":["2015-10-28_在文化广场进行拔河比赛，我们区队拿了第一。这天天气很好，后面一群其他专业的学生在训练.jpg","2015-10-28_大一的小五.jpg"],"year":2015}}]}